jdv_typecheck/__init__.py
jdv_typecheck/__version__.py
jdv_typecheck/_tests.py
jdv_typecheck/check.py
jdv_typecheck-1.0.1.dist-info/WHEEL
jdv_typecheck-1.0.1.dist-info/METADATA
jdv_typecheck-1.0.1.dist-info/RECORD
