Metadata-Version: 2.1
Name: jdv-typecheck
Version: 1.0.1
Summary: 
Author: Justin Vrana
Author-email: justin.vrana@gmail.com
Requires-Python: >=3.8,<4.0
Classifier: Programming Language :: Python :: 3
Classifier: Programming Language :: Python :: 3.8
Classifier: Programming Language :: Python :: 3.9
Classifier: Programming Language :: Python :: 3.10
Requires-Dist: typing-extensions (>=4.2.0,<5.0.0)
